<?xml version="1.0" encoding="UTF-8" standalone="yes"?><title-info rev="0"><id>NPUA81174</id><console>ps3</console><media-type>edi</media-type><name>LittleBigPlanet™3 Digital Version BETA</name><name lang="2">LittleBigPlanet™3 (version digitale) BETA</name><name lang="3">LittleBigPlanet™3 - Versión digital BETA</name><name lang="4">LittleBigPlanet™3: Digitale Version BETA</name><name lang="5">LittleBigPlanet™3 - versione digitale BETA</name><name lang="6">LittleBigPlanet™3 digitale versie BETA</name><name lang="7">Versão Digital LittleBigPlanet™3 BETA</name><name lang="8">Электронная версия LittleBigPlanet™3 BETA</name><name lang="9">LittleBigPlanet™3 디지털 에디션 BETA</name><name lang="10">LittleBigPlanet™3 下載版 BETA</name><name lang="11">LittleBigPlanet™3 下載版 BETA</name><name lang="12">LittleBigPlanet™3-digitaaliversio BETA</name><name lang="13">LittleBigPlanet™3 - digital version BETA</name><name lang="14">LittleBigPlanet™3, digital version BETA</name><name lang="15">LittleBigPlanet™3 – Nedlastingsversjon BETA</name><name lang="16">LittleBigPlanet™3 - Edycja cyfrowa BETA</name><parental-level>3</parental-level><icon type="320x176">http://tmdb.np.dl.playstation.net/tmdb/NPUA81174_00_363899F5C7B0A54C336C6F52FA095D4FC081C554/ICON0.PNG</icon><icon lang="0" type="320x176">http://tmdb.np.dl.playstation.net/tmdb/NPUA81174_00_363899F5C7B0A54C336C6F52FA095D4FC081C554/ICON0_00.PNG</icon><resolution>480,576,720,480SQ,576SQ</resolution><sound-format>2LPCM,5.1LPCM,Dolby,DTS</sound-format></title-info>